patatt/__init__.py
patatt-0.6.3.data/data/share/man/man5/patatt.5
patatt-0.6.3.dist-info/COPYING
patatt-0.6.3.dist-info/METADATA
patatt-0.6.3.dist-info/WHEEL
patatt-0.6.3.dist-info/entry_points.txt
patatt-0.6.3.dist-info/top_level.txt
patatt-0.6.3.dist-info/RECORD
