Metadata-Version: 2.1
Name: patatt
Version: 0.6.3
Summary: A simple library to add cryptographic attestation to patches sent via email
Home-page: https://git.kernel.org/pub/scm/utils/patatt/patatt.git/about/
Author: Konstantin Ryabitsev
Author-email: mricon@kernel.org
License: MIT-0
Keywords: git,patches,attestation
Requires-Python: >=3.6
License-File: COPYING
